quantis/__init__.py
quantis/app.py
quantis/app_legacy.py
quantis/cash_or_new.py
quantis/df_prep.py
quantis/filetypes.py
quantis/knn_imputation.py
quantis/log_setup.py
quantis/ms1diffacto.py
quantis/ncbi_species_parser.py
quantis/open_tsv_files_dialog.py
quantis/string_request.py
quantis/utils.py
quantis/assets/dragula.css
quantis/assets/resizer.js
quantis/assets/scripts.js
quantis/assets/style copy.css
quantis/assets/style.css
Quantis-0.7.dist-info/LICENSE
Quantis-0.7.dist-info/METADATA
Quantis-0.7.dist-info/WHEEL
Quantis-0.7.dist-info/entry_points.txt
Quantis-0.7.dist-info/top_level.txt
Quantis-0.7.dist-info/RECORD
